[
    {
        "key": "datr",
        "value": "72sJZ59HCtNiQ2tFVwx3I5sM",
        "domain": "facebook.com",
        "path": "/",
        "hostOnly": false,
        "creation": "2024-10-13T10:56:03.521Z",
        "lastAccessed": "2024-10-13T10:56:03.521Z"
    },
    {
        "key": "sb",
        "value": "72sJZzjwZW1ZYW0K9CMQekPB",
        "domain": "facebook.com",
        "path": "/",
        "hostOnly": false,
        "creation": "2024-10-13T10:56:03.521Z",
        "lastAccessed": "2024-10-13T10:56:03.521Z"
    },
    {
        "key": "c_user",
        "value": "61554699625261",
        "domain": "facebook.com",
        "path": "/",
        "hostOnly": false,
        "creation": "2024-10-13T10:56:03.521Z",
        "lastAccessed": "2024-10-13T10:56:03.521Z"
    },
    {
        "key": "vpd",
        "value": "v1%3B736x393x2.75",
        "domain": "facebook.com",
        "path": "/",
        "hostOnly": false,
        "creation": "2024-10-13T10:56:03.521Z",
        "lastAccessed": "2024-10-13T10:56:03.521Z"
    },
    {
        "key": "dpr",
        "value": "2.75",
        "domain": "facebook.com",
        "path": "/",
        "hostOnly": false,
        "creation": "2024-10-13T10:56:03.521Z",
        "lastAccessed": "2024-10-13T10:56:03.522Z"
    },
    {
        "key": "m_pixel_ratio",
        "value": "2.75",
        "domain": "facebook.com",
        "path": "/",
        "hostOnly": false,
        "creation": "2024-10-13T10:56:03.522Z",
        "lastAccessed": "2024-10-13T10:56:03.522Z"
    },
    {
        "key": "x-referer",
        "value": "eyJyIjoiL2xvZ2luL2ZvcmdldF9yZWNvdmVyeS8%2FbmV4dD0lMkYmcmVmPWFjY291bnRzX2NlbnRlcl9jaGFuZ2VfcGFzc3dvcmQiLCJoIjoiL2xvZ2luL2ZvcmdldF9yZWNvdmVyeS8%2FbmV4dD0lMkYmcmVmPWFjY291bnRzX2NlbnRlcl9jaGFuZ2VfcGFzc3dvcmQiLCJzIjoibSJ9",
        "domain": "facebook.com",
        "path": "/",
        "hostOnly": false,
        "creation": "2024-10-13T10:56:03.522Z",
        "lastAccessed": "2024-10-13T10:56:03.522Z"
    },
    {
        "key": "wd",
        "value": "393x736",
        "domain": "facebook.com",
        "path": "/",
        "hostOnly": false,
        "creation": "2024-10-13T10:56:03.522Z",
        "lastAccessed": "2024-10-13T10:56:03.522Z"
    },
    {
        "key": "fr",
        "value": "0FJTAKkgmXPWY64Qf.AWWnGnyb8bXUVvUjoeMJ-kvOtj4.BnCWvv..AAA.0.0.BnC6c3.AWXSvMrkYwk",
        "domain": "facebook.com",
        "path": "/",
        "hostOnly": false,
        "creation": "2024-10-13T10:56:03.522Z",
        "lastAccessed": "2024-10-13T10:56:03.522Z"
    },
    {
        "key": "xs",
        "value": "28%3AMwicJAGluonjAA%3A2%3A1728816956%3A-1%3A15401",
        "domain": "facebook.com",
        "path": "/",
        "hostOnly": false,
        "creation": "2024-10-13T10:56:03.522Z",
        "lastAccessed": "2024-10-13T10:56:03.522Z"
    },
    {
        "key": "fbl_st",
        "value": "101629277%3BT%3A28813615",
        "domain": "facebook.com",
        "path": "/",
        "hostOnly": false,
        "creation": "2024-10-13T10:56:03.522Z",
        "lastAccessed": "2024-10-13T10:56:03.522Z"
    }
]
